<?xml version="1.0" encoding="UTF-8"?>
<ruleset name="HomeDash PMD Ruleset"
         xmlns="http://pmd.sourceforge.net/ruleset/2.0.0"
         xmlns:xsi="http://www.w3.org/2001/XMLSchema-instance"
         xsi:schemaLocation="http://pmd.sourceforge.net/ruleset/2.0.0 http://pmd.sourceforge.net/ruleset_2_0_0.xsd">

    <description>
        HomeDash椤圭洰浠ｇ爜璐ㄩ噺妫€鏌ヨ鍒欓泦
        閬靛惊杞婚噺鍖栧師鍒欙紝鍙鏌ュ叧閿唬鐮佽川閲忛棶棰?
    </description>

    <!-- 鏈€浣冲疄璺佃鍒?-->
    <rule ref="category/java/bestpractices.xml">
        <!-- 鎺掗櫎涓€浜涗笉閫傜敤浜庨」鐩殑瑙勫垯 -->
        <exclude name="GuardLogStatement"/>
        <exclude name="JUnitTestContainsTooManyAsserts"/>
        <exclude name="JUnitAssertionsShouldIncludeMessage"/>
    </rule>

    <!-- 浠ｇ爜椋庢牸瑙勫垯 -->
    <rule ref="category/java/codestyle.xml">
        <!-- 鎺掗櫎涓€浜涜繃浜庝弗鏍肩殑瑙勫垯 -->
        <exclude name="AtLeastOneConstructor"/>
        <exclude name="CallSuperInConstructor"/>
        <exclude name="CommentDefaultAccessModifier"/>
        <exclude name="ConfusingTernary"/>
        <exclude name="LongVariable"/>
        <exclude name="OnlyOneReturn"/>
        <exclude name="ShortClassName"/>
        <exclude name="ShortMethodName"/>
        <exclude name="ShortVariable"/>
        <exclude name="TooManyStaticImports"/>
    </rule>

    <!-- 璁捐瑙勫垯 -->
    <rule ref="category/java/design.xml">
        <!-- 鎺掗櫎涓€浜涗笉閫傜敤浜庨」鐩殑瑙勫垯 -->
        <exclude name="AvoidCatchingGenericException"/>
        <exclude name="CouplingBetweenObjects"/>
        <exclude name="DataClass"/>
        <exclude name="ExcessiveImports"/>
        <exclude name="LawOfDemeter"/>
        <exclude name="LoosePackageCoupling"/>
        <exclude name="TooManyFields"/>
        <exclude name="TooManyMethods"/>
    </rule>

    <!-- 鏂囨。瑙勫垯 -->
    <rule ref="category/java/documentation.xml">
        <!-- 鎺掗櫎娉ㄩ噴瑕佹眰瑙勫垯锛屼繚鎸佽交閲忓寲 -->
        <exclude name="CommentRequired"/>
        <exclude name="CommentSize"/>
    </rule>

    <!-- 閿欒澶勭悊瑙勫垯 -->
    <rule ref="category/java/errorprone.xml">
        <!-- 鎺掗櫎涓€浜涗笉閫傜敤浜庨」鐩殑瑙勫垯 -->
        <exclude name="AvoidDuplicateLiterals"/>
        <exclude name="AvoidFieldNameMatchingMethodName"/>
        <exclude name="AvoidFieldNameMatchingTypeName"/>
        <exclude name="AvoidLiteralsInIfCondition"/>
        <exclude name="MissingSerialVersionUID"/>
        <exclude name="NullAssignment"/>
    </rule>

    <!-- 澶氱嚎绋嬭鍒?-->
    <rule ref="category/java/multithreading.xml">
        <!-- 鎺掗櫎涓€浜涗笉閫傜敤浜庨」鐩殑瑙勫垯 -->
        <exclude name="DoNotUseThreads"/>
        <exclude name="UseConcurrentHashMap"/>
    </rule>

    <!-- 鎬ц兘瑙勫垯 -->
    <rule ref="category/java/performance.xml">
        <!-- 鎺掗櫎涓€浜涗笉閫傜敤浜庨」鐩殑瑙勫垯 -->
        <exclude name="AvoidInstantiatingObjectsInLoops"/>
    </rule>

    <!-- 瀹夊叏瑙勫垯 -->
    <rule ref="category/java/security.xml"/>

</ruleset>

